README.md
setup.cfg
setup.py
src/pyMez/Modules.html
src/pyMez/__init__.py
src/pyMez.egg-info/PKG-INFO
src/pyMez.egg-info/SOURCES.txt
src/pyMez.egg-info/dependency_links.txt
src/pyMez.egg-info/requires.txt
src/pyMez.egg-info/top_level.txt
src/pyMez/Code/__init__.py
src/pyMez/Code/Analysis/Fitting.py
src/pyMez/Code/Analysis/GeneralAnalysis.py
src/pyMez/Code/Analysis/Interpolation.py
src/pyMez/Code/Analysis/NISTUncertainty.py
src/pyMez/Code/Analysis/ProgramAnalysis.py
src/pyMez/Code/Analysis/Reports.py
src/pyMez/Code/Analysis/SParameter.py
src/pyMez/Code/Analysis/Transformations.py
src/pyMez/Code/Analysis/Uncertainty.py
src/pyMez/Code/Analysis/__init__.py
src/pyMez/Code/DataHandlers/AbstractDjangoModels.py
src/pyMez/Code/DataHandlers/GeneralModels.py
src/pyMez/Code/DataHandlers/GraphModels.py
src/pyMez/Code/DataHandlers/HTMLModels.py
src/pyMez/Code/DataHandlers/MUFModels.py
src/pyMez/Code/DataHandlers/NISTModels.py
src/pyMez/Code/DataHandlers/RadiCALModels.py
src/pyMez/Code/DataHandlers/StatistiCALModels.py
src/pyMez/Code/DataHandlers/TouchstoneModels.py
src/pyMez/Code/DataHandlers/Translations.py
src/pyMez/Code/DataHandlers/XMLModels.py
src/pyMez/Code/DataHandlers/ZipModels.py
src/pyMez/Code/DataHandlers/__init__.py
src/pyMez/Code/DataHandlers/Tests/000146c.txt
src/pyMez/Code/DataHandlers/Tests/20160301_30ft_cable_0.s2p
src/pyMez/Code/DataHandlers/Tests/700083a.txt
src/pyMez/Code/DataHandlers/Tests/700083b.txt
src/pyMez/Code/DataHandlers/Tests/700196a.txt
src/pyMez/Code/DataHandlers/Tests/700196b.txt
src/pyMez/Code/DataHandlers/Tests/700437.txt
src/pyMez/Code/DataHandlers/Tests/704b.S2P
src/pyMez/Code/DataHandlers/Tests/922729a.txt
src/pyMez/Code/DataHandlers/Tests/922729b.txt
src/pyMez/Code/DataHandlers/Tests/922729c.txt
src/pyMez/Code/DataHandlers/Tests/B7_baseline_50ohm_OR2_10n0_4p0_REV2_EVB1_01new.s3p
src/pyMez/Code/DataHandlers/Tests/CH_6.s2p
src/pyMez/Code/DataHandlers/Tests/CTNP13_sm_112907.txt
src/pyMez/Code/DataHandlers/Tests/CalCoefficients.txt
src/pyMez/Code/DataHandlers/Tests/Canal_36.S2P
src/pyMez/Code/DataHandlers/Tests/Data_Table_021311_1.xml
src/pyMez/Code/DataHandlers/Tests/Data_Table_20160223_001.xml
