Metadata-Version: 1.1
Name: pyMez
Version: 1.3.25
Summary: Measurement, Analysis and Data Management Software. To load the API interface use from pyMez import *.
Home-page: https://github.com/aricsanders/pyMez
Author: Aric Sanders
Author-email: aric.sanders@gmail.com
License: MIT
Download-URL: https://github.com/aricsanders/pyMez.git
Keywords: measurement,data handling,example
Platform: UNKNOWN
Classifier: Programming Language :: Python
